carling/__init__.py
carling/categorical.py
carling/group.py
carling/io/__init__.py
carling/io/avro_schema.py
carling/iter_utils/__init__.py
carling/iter_utils/iter_utils.py
carling/mapping.py
carling/py.typed
carling/test_utils/__init__.py
carling/test_utils/test_utils.py
carling/util.py
carling-0.4.0.dist-info/LICENSE
carling-0.4.0.dist-info/METADATA
carling-0.4.0.dist-info/WHEEL
carling-0.4.0.dist-info/RECORD
