Metadata-Version: 2.1
Name: carling
Version: 0.4.0
Summary: Useful transforms for supporting apache beam pipelines.
Home-page: https://github.com/mc-digital/carling
License: Apache-2.0
Author: Adam Moore
Author-email: adam@mcdigital.jp
Requires-Python: >=3.8,<3.12
Classifier: License :: OSI Approved :: Apache Software License
Classifier: Programming Language :: Python :: 3
Classifier: Programming Language :: Python :: 3.8
Classifier: Programming Language :: Python :: 3.9
Classifier: Programming Language :: Python :: 3.10
Classifier: Programming Language :: Python :: 3.11
Requires-Dist: apache-beam (>=2.49.0,<3.0.0)
Requires-Dist: deepdiff (>=5.7,<7.0)
Project-URL: Repository, https://github.com/mc-digital/carling
